{"_type":"export","__export_format":4,"__export_date":"2024-03-21T23:19:50.324Z","__export_source":"insomnia.desktop.app:v8.6.1","resources":[{"_id":"req_8dbf87a8fb8e49cdaf7537aea9d8d2c7","parentId":"fld_1b23be7fff7749c5931abe8d9c81429e","modified":1711063135239,"created":1711059478794,"url":"{{ _.BASE_URL }}/invoices","name":"Get invoices","description":"","method":"GET","body":{},"parameters":[],"headers":[{"name":"User-Agent","value":"insomnia/2023.5.8"}],"authentication":{},"metaSortKey":-1711063124724,"isPrivate":false,"pathParameters":[],"settingStoreCookies":true,"settingSendCookies":true,"settingDisableRenderRequestBody":false,"settingEncodeUrl":true,"settingRebuildPath":true,"settingFollowRedirects":"global","_type":"request"},{"_id":"fld_1b23be7fff7749c5931abe8d9c81429e","parentId":"wrk_57fc9a205ede4486b4d60c53292fc9b1","modified":1711063098360,"created":1711063098360,"name":"Invoices","description":"","environment":{},"environmentPropertyOrder":null,"metaSortKey":-1711063098360,"_type":"request_group"},{"_id":"wrk_57fc9a205ede4486b4d60c53292fc9b1","parentId":null,"modified":1711058805132,"created":1711058805132,"name":"BizTime","description":"","scope":"collection","_type":"workspace"},{"_id":"req_56c1dce8d1e14ffd807b53ad07055412","parentId":"fld_1b23be7fff7749c5931abe8d9c81429e","modified":1711063133064,"created":1711060159151,"url":"{{ _.BASE_URL }}/invoices/3","name":"Get invoice","description":"","method":"GET","body":{},"parameters":[],"headers":[{"name":"User-Agent","value":"insomnia/2023.5.8"}],"authentication":{},"metaSortKey":-1711063124624,"isPrivate":false,"pathParameters":[],"settingStoreCookies":true,"settingSendCookies":true,"settingDisableRenderRequestBody":false,"settingEncodeUrl":true,"settingRebuildPath":true,"settingFollowRedirects":"global","_type":"request"},{"_id":"req_a1d1b41793344c69929d2ebee0e53735","parentId":"fld_1b23be7fff7749c5931abe8d9c81429e","modified":1711063128442,"created":1711059549556,"url":"{{ _.BASE_URL }}/invoices","name":"Add invoice","description":"","method":"POST","body":{"mimeType":"application/json","text":"{\n\t\"comp_code\": \"apple\",\n\t\"amt\": \"5000\"\n}"},"parameters":[],"headers":[{"name":"Content-Type","value":"application/json"},{"name":"User-Agent","value":"insomnia/2023.5.8"}],"authentication":{},"metaSortKey":-1711063124524,"isPrivate":false,"pathParameters":[],"settingStoreCookies":true,"settingSendCookies":true,"settingDisableRenderRequestBody":false,"settingEncodeUrl":true,"settingRebuildPath":true,"settingFollowRedirects":"global","_type":"request"},{"_id":"req_04bdffe76b604745a98bef27e41bd5eb","parentId":"fld_1b23be7fff7749c5931abe8d9c81429e","modified":1711063126584,"created":1711060122596,"url":"{{ _.BASE_URL }}/invoices/30","name":"Edit invoice","description":"","method":"PUT","body":{"mimeType":"application/json","text":"{\n\t\"amt\": \"50\"\n}"},"parameters":[],"headers":[{"name":"Content-Type","value":"application/json"},{"name":"User-Agent","value":"insomnia/2023.5.8"}],"authentication":{},"metaSortKey":-1711063124424,"isPrivate":false,"pathParameters":[],"settingStoreCookies":true,"settingSendCookies":true,"settingDisableRenderRequestBody":false,"settingEncodeUrl":true,"settingRebuildPath":true,"settingFollowRedirects":"global","_type":"request"},{"_id":"req_aefd1a1b122e4ba69c00eb7f840840c9","parentId":"fld_1b23be7fff7749c5931abe8d9c81429e","modified":1711063124366,"created":1711060163196,"url":"{{ _.BASE_URL }}/invoices/3","name":"DELETE invoice","description":"","method":"DELETE","body":{},"parameters":[],"headers":[{"name":"User-Agent","value":"insomnia/8.6.1"}],"authentication":{},"metaSortKey":-1711063124324,"isPrivate":false,"pathParameters":[],"settingStoreCookies":true,"settingSendCookies":true,"settingDisableRenderRequestBody":false,"settingEncodeUrl":true,"settingRebuildPath":true,"settingFollowRedirects":"global","_type":"request"},{"_id":"req_c46c6e714d684fcf86ccb17a8c901d97","parentId":"fld_1d0f8dcdcbd14baaa7c4a186dca93728","modified":1711063120882,"created":1711055625006,"url":"{{ _.BASE_URL }}/companies/tesla","name":"Edit company","description":"","method":"PUT","body":{"mimeType":"application/json","text":"{\n\t\"name\": \"tesla inc\",\n\t\"description\": \"ai company\"\n}"},"parameters":[],"headers":[{"name":"Content-Type","value":"application/json"},{"name":"User-Agent","value":"insomnia/2023.5.8"}],"authentication":{},"metaSortKey":-1711063108742,"isPrivate":false,"pathParameters":[],"settingStoreCookies":true,"settingSendCookies":true,"settingDisableRenderRequestBody":false,"settingEncodeUrl":true,"settingRebuildPath":true,"settingFollowRedirects":"global","_type":"request"},{"_id":"fld_1d0f8dcdcbd14baaa7c4a186dca93728","parentId":"wrk_57fc9a205ede4486b4d60c53292fc9b1","modified":1711063092054,"created":1711063092054,"name":"Companies","description":"","environment":{},"environmentPropertyOrder":null,"metaSortKey":-1711063092054,"_type":"request_group"},{"_id":"req_861ee86cbb3d42649eae1356b3f26252","parentId":"fld_1d0f8dcdcbd14baaa7c4a186dca93728","modified":1711063118147,"created":1711055989273,"url":"{{ _.BASE_URL }}/companies/tesla","name":"Delete company","description":"","method":"DELETE","body":{},"parameters":[],"headers":[{"name":"User-Agent","value":"insomnia/2023.5.8"}],"authentication":{},"metaSortKey":-1711063108642,"isPrivate":false,"pathParameters":[],"settingStoreCookies":true,"settingSendCookies":true,"settingDisableRenderRequestBody":false,"settingEncodeUrl":true,"settingRebuildPath":true,"settingFollowRedirects":"global","_type":"request"},{"_id":"req_fb8f184c19374bad9ecd07346709b3ce","parentId":"fld_1d0f8dcdcbd14baaa7c4a186dca93728","modified":1711063115415,"created":1711048815448,"url":"{{ _.BASE_URL }}/companies","name":"Add company","description":"","method":"POST","body":{"mimeType":"application/json","text":"{\n\t\"code\": \"something\", \n\t\"name\": \"here\", \n\t\"description\": \"there\"\n}"},"parameters":[],"headers":[{"name":"Content-Type","value":"application/json"},{"name":"User-Agent","value":"insomnia/2023.5.8"}],"authentication":{},"metaSortKey":-1711063108542,"isPrivate":false,"pathParameters":[],"settingStoreCookies":true,"settingSendCookies":true,"settingDisableRenderRequestBody":false,"settingEncodeUrl":true,"settingRebuildPath":true,"settingFollowRedirects":"global","_type":"request"},{"_id":"req_30c343c1f349476182a6fee513cd2faa","parentId":"fld_1d0f8dcdcbd14baaa7c4a186dca93728","modified":1711063111355,"created":1711048806417,"url":"{{ _.BASE_URL }}/companies/apple","name":"Get company","description":"","method":"GET","body":{},"parameters":[],"headers":[{"name":"User-Agent","value":"insomnia/2023.5.8"}],"authentication":{},"metaSortKey":-1711063108442,"isPrivate":false,"pathParameters":[],"settingStoreCookies":true,"settingSendCookies":true,"settingDisableRenderRequestBody":false,"settingEncodeUrl":true,"settingRebuildPath":true,"settingFollowRedirects":"global","_type":"request"},{"_id":"req_bd4b1d74d3304954ac00f40eca304daa","parentId":"fld_1d0f8dcdcbd14baaa7c4a186dca93728","modified":1711063108383,"created":1711048793582,"url":"{{ _.BASE_URL }}/companies","name":"Get all companies","description":"","method":"GET","body":{},"parameters":[],"headers":[{"name":"User-Agent","value":"insomnia/2023.5.8"}],"authentication":{},"metaSortKey":-1711063108342,"isPrivate":false,"pathParameters":[],"settingStoreCookies":true,"settingSendCookies":true,"settingDisableRenderRequestBody":false,"settingEncodeUrl":true,"settingRebuildPath":true,"settingFollowRedirects":"global","_type":"request"},{"_id":"env_aa029355fae3a7c76ace1d218e71e354dbf966ab","parentId":"wrk_57fc9a205ede4486b4d60c53292fc9b1","modified":1711058859592,"created":1711058805133,"name":"Base Environment","data":{"BASE_URL":"http://localhost:3000"},"dataPropertyOrder":{"&":["BASE_URL"]},"color":null,"isPrivate":false,"metaSortKey":1711058805133,"_type":"environment"},{"_id":"jar_aa029355fae3a7c76ace1d218e71e354dbf966ab","parentId":"wrk_57fc9a205ede4486b4d60c53292fc9b1","modified":1711058805134,"created":1711058805134,"name":"Default Jar","cookies":[],"_type":"cookie_jar"}]}